aganitha/main.py
aganitha/pubmed.py
aganitha-0.1.0.dist-info/entry_points.txt
aganitha-0.1.0.dist-info/METADATA
aganitha-0.1.0.dist-info/WHEEL
aganitha-0.1.0.dist-info/RECORD
