Metadata-Version: 2.3
Name: aganitha
Version: 0.1.0
Summary: Brief description of what the project does
Author: rautkaveri24
Author-email: rautkaveri24@gmail.com
Requires-Python: >=3.11
Classifier: Programming Language :: Python :: 3
Classifier: Programming Language :: Python :: 3.11
Classifier: Programming Language :: Python :: 3.12
Classifier: Programming Language :: Python :: 3.13
Requires-Dist: requests (>=2.32.3,<3.0.0)
